Orange_SNOM-0.1.0-py3.11-nspkg.pth
orangecontrib/snom/__init__.py
orangecontrib/snom/model/__init__.py
orangecontrib/snom/model/snompy.py
orangecontrib/snom/preprocess/__init__.py
orangecontrib/snom/preprocess/phase_unwrap.py
orangecontrib/snom/preprocess/utils.py
orangecontrib/snom/tests/__init__.py
orangecontrib/snom/tests/snompy_examples.py
orangecontrib/snom/tests/test_preprocess.py
orangecontrib/snom/tests/test_snompy.py
orangecontrib/snom/widgets/__init__.py
orangecontrib/snom/widgets/owpreprocessimage.py
orangecontrib/snom/widgets/owsnompy.py
orangecontrib/snom/widgets/snompy_compute.py
orangecontrib/snom/widgets/snompy_util.py
orangecontrib/snom/widgets/icons/category.svg
orangecontrib/snom/widgets/icons/preprocessimage.svg
orangecontrib/snom/widgets/icons/snompy.svg
orangecontrib/snom/widgets/preprocessors/__init__.py
orangecontrib/snom/widgets/preprocessors/background_fit.py
orangecontrib/snom/widgets/preprocessors/linelevel.py
orangecontrib/snom/widgets/preprocessors/phase_rotation.py
orangecontrib/snom/widgets/preprocessors/phase_unwrap.py
orangecontrib/snom/widgets/preprocessors/registry.py
orangecontrib/snom/widgets/preprocessors/self_reference.py
orangecontrib/snom/widgets/preprocessors/simple_normalize.py
orangecontrib/snom/widgets/preprocessors/utils.py
orangecontrib/snom/widgets/tests/__init__.py
orangecontrib/snom/widgets/tests/test_owpreprocessimage.py
orange_snom-0.1.0.dist-info/METADATA
orange_snom-0.1.0.dist-info/WHEEL
orange_snom-0.1.0.dist-info/entry_points.txt
orange_snom-0.1.0.dist-info/namespace_packages.txt
orange_snom-0.1.0.dist-info/top_level.txt
orange_snom-0.1.0.dist-info/RECORD
