Metadata-Version: 2.4
Name: Orange-SNOM
Version: 0.1.0
Summary: SNOM add-on for Orange data mining software package.
Home-page: https://github.com/quasars/orange-snom
Author: Canadian Light Source, Biolab UL, Soleil
Author-email: info@biolab.si
Maintainer: Marko Toplak
License: GPL3+
Project-URL: Bug Tracker, https://github.com/quasars/orange-snom/issues
Project-URL: Source Code, https://github.com/quasars/orange-snom
Keywords: 'orange3 add-on'
Requires-Python: >=3.11
Requires-Dist: Orange3>=3.35.0
Requires-Dist: orange-spectroscopy>=0.7.2
Requires-Dist: numpy>=1.24.0
Requires-Dist: pySNOM>=0.1.0
Requires-Dist: snompy>=0.1.7
Provides-Extra: doc
Requires-Dist: sphinx; extra == "doc"
Requires-Dist: recommonmark; extra == "doc"
Requires-Dist: sphinx_rtd_theme; extra == "doc"
Provides-Extra: test
Requires-Dist: pytest; extra == "test"
Requires-Dist: coverage; extra == "test"
Requires-Dist: flake8; extra == "test"
Requires-Dist: flake8-bugbear; extra == "test"
Requires-Dist: black; extra == "test"
